binance_s3_trades/__init__.py
binance_s3_trades/cli.py
binance_s3_trades/core.py
binance_s3_trades/downloader.py
binance_s3_trades/logging.py
binance_s3_trades/types.py
binance_s3_trades/utils.py
binance_s3_trades-0.2.2.dist-info/METADATA
binance_s3_trades-0.2.2.dist-info/WHEEL
binance_s3_trades-0.2.2.dist-info/licenses/LICENSE.md
binance_s3_trades-0.2.2.dist-info/RECORD
