Metadata-Version: 2.4
Name: binance-s3-trades
Version: 0.2.2
Summary: Seamlessly list and download Binance spot trade .zip files from the public S3 bucket
License-Expression: MIT
License-File: LICENSE.md
Keywords: binance,s3,trades,downloader
Author: Michal Polit
Author-email: mpolit@protonmail.com
Requires-Python: >=3.13,<4.0
Classifier: Programming Language :: Python :: 3
Classifier: Programming Language :: Python :: 3.13
Classifier: Programming Language :: Python :: 3.14
Requires-Dist: boto3 (==1.42.29)
Requires-Dist: typer (>=0.21.1,<0.22.0)
Project-URL: Homepage, https://github.com/mpolit/binance-s3-trades
Project-URL: Repository, https://github.com/mpolit/binance-s3-trades
